<?xml version="1.0" standalone="yes"?>
<NewDataSet>
  <InventoryItems>
    <ID>1</ID>
    <categoryID>-1</categoryID>
    <Name>Jungle Picture Projector</Name>
    <Description>Flashlight comes with assorted clear disks with images of your favorite theme. Place a disk on the end of te flashlight and an image is projected onto the wall, ceiling or other flat surface. Requires two "AA" batteries. (not included) Ages 5 &amp; up 6"</Description>
    <UPC>085761075467</UPC>
    <Price>5.99</Price>
    <WholesalePrice>1.5</WholesalePrice>
    <SalePrice>0</SalePrice>
    <OnSale>false</OnSale>
    <Manufacturer>toysmith</Manufacturer>
    <Quantity>6</Quantity>
    <PicturePath>C:\Program Files\SCTech\Voodoo Cash Register\data\inventoryImages\jungleMiniProjector.jpg</PicturePath>
    <DateCreated>2012-02-16T12:38:15.8125-07:00</DateCreated>
  </InventoryItems>
  <InventoryItems>
    <ID>2</ID>
    <categoryID>-1</categoryID>
    <Name>Wooden Pop Gun</Name>
    <UPC>0085761062207</UPC>
    <Price>6.95</Price>
    <WholesalePrice>1.5</WholesalePrice>
    <SalePrice>4.95</SalePrice>
    <OnSale>false</OnSale>
    <Manufacturer>Toysmith</Manufacturer>
    <Quantity>12</Quantity>
    <PicturePath>C:\Program Files\SCTech\Voodoo Cash Register\data\inventoryImages\imageNotAvailable.jpg</PicturePath>
    <DateCreated>2012-02-16T12:40:01.65625-07:00</DateCreated>
  </InventoryItems>
  <InventoryItems>
    <ID>3</ID>
    <categoryID>-1</categoryID>
    <Name>Wooden Pop Gun</Name>
    <UPC>0085761062207</UPC>
    <Price>6.95</Price>
    <WholesalePrice>1.5</WholesalePrice>
    <SalePrice>4.95</SalePrice>
    <OnSale>false</OnSale>
    <Manufacturer>Toysmith</Manufacturer>
    <Quantity>8</Quantity>
    <PicturePath>C:\Program Files\SCTech\Voodoo Cash Register\data\inventoryImages\imageNotAvailable.jpg</PicturePath>
    <DateCreated>2012-02-16T12:40:53-07:00</DateCreated>
  </InventoryItems>
  <InventoryItems>
    <ID>4</ID>
    <categoryID>-1</categoryID>
    <Name>Voice Transformer</Name>
    <Description>Alter your voice with this 4 x 2.5 inch transformer. It has settings to create 9 different voice effects and features a corded external microphone. Requires one 9V battery, not included. Assorted colors. 
</Description>
    <UPC>085761013773</UPC>
    <Price>11.99</Price>
    <WholesalePrice>4.5</WholesalePrice>
    <SalePrice>0</SalePrice>
    <OnSale>false</OnSale>
    <Manufacturer>toysmith</Manufacturer>
    <Quantity>12</Quantity>
    <PicturePath>C:\Program Files\SCTech\Voodoo Cash Register\data\inventoryImages\voicetransformer.jpg</PicturePath>
    <DateCreated>2012-02-16T12:41:14.453125-07:00</DateCreated>
  </InventoryItems>
  <InventoryItems>
    <ID>5</ID>
    <categoryID>-1</categoryID>
    <Name>Binoculars 6 X 35</Name>
    <Description>These durable 5.25 inch binoculars feature 6 X 35 power, and come in two assorted translucent colors. Detachable neck strap included.</Description>
    <UPC>085761069176</UPC>
    <Price>14.5</Price>
    <WholesalePrice>5.5</WholesalePrice>
    <SalePrice>0</SalePrice>
    <OnSale>false</OnSale>
    <Manufacturer>toysmith</Manufacturer>
    <Quantity>12</Quantity>
    <PicturePath>C:\Program Files\SCTech\Voodoo Cash Register\data\inventoryImages\binoculars.jpg</PicturePath>
    <DateCreated>2012-02-16T12:41:37.28125-07:00</DateCreated>
  </InventoryItems>
  <InventoryItems>
    <ID>6</ID>
    <categoryID>-1</categoryID>
    <Name>Mystical Garden</Name>
    <UPC>0085761012882</UPC>
    <Price>5.99</Price>
    <WholesalePrice>2.5</WholesalePrice>
    <SalePrice>0</SalePrice>
    <OnSale>false</OnSale>
    <Manufacturer>Toysmith</Manufacturer>
    <Quantity>12</Quantity>
    <PicturePath>C:\Program Files\SCTech\Voodoo Cash Register\data\inventoryImages\imageNotAvailable.jpg</PicturePath>
    <DateCreated>2012-02-16T12:42:52.078125-07:00</DateCreated>
  </InventoryItems>
  <InventoryItems>
    <ID>7</ID>
    <categoryID>-1</categoryID>
    <Name>Playing Cards 2 Deck</Name>
    <UPC>639277336057</UPC>
    <Price>3.5</Price>
    <WholesalePrice>1</WholesalePrice>
    <SalePrice>0</SalePrice>
    <OnSale>false</OnSale>
    <Manufacturer>Dollar Tree</Manufacturer>
    <Quantity>2</Quantity>
    <PicturePath>C:\Program Files\SCTech\Voodoo Cash Register\data\inventoryImages\imageNotAvailable.jpg</PicturePath>
    <DateCreated>2012-02-16T12:43:20.78125-07:00</DateCreated>
  </InventoryItems>
  <InventoryItems>
    <ID>8</ID>
    <categoryID>-1</categoryID>
    <Name>Playing Cards 2 Deck</Name>
    <UPC>639277336057</UPC>
    <Price>3.5</Price>
    <WholesalePrice>1</WholesalePrice>
    <SalePrice>0</SalePrice>
    <OnSale>false</OnSale>
    <Manufacturer>Dollar Tree</Manufacturer>
    <Quantity>3</Quantity>
    <PicturePath>C:\Program Files\SCTech\Voodoo Cash Register\data\inventoryImages\imageNotAvailable.jpg</PicturePath>
    <DateCreated>2012-02-16T12:44:11.1875-07:00</DateCreated>
  </InventoryItems>
  <InventoryItems>
    <ID>9</ID>
    <categoryID>-1</categoryID>
    <Name>Playing Cards 2 Deck</Name>
    <UPC>639277336057</UPC>
    <Price>3.5</Price>
    <WholesalePrice>1</WholesalePrice>
    <SalePrice>0</SalePrice>
    <OnSale>false</OnSale>
    <Manufacturer>Dollar Tree</Manufacturer>
    <Quantity>3</Quantity>
    <PicturePath>C:\Program Files\SCTech\Voodoo Cash Register\data\inventoryImages\imageNotAvailable.jpg</PicturePath>
    <DateCreated>2012-02-16T12:44:15.71875-07:00</DateCreated>
  </InventoryItems>
  <InventoryItems>
    <ID>10</ID>
    <categoryID>-1</categoryID>
    <Name>Lazer fingers</Name>
    <Description>Create your own amazing light show with these sets of mini finger lights. Each set includes four .75 x .5 inch lights with elastic bands. Each light projects a different color.</Description>
    <UPC>085761146358</UPC>
    <Price>4.99</Price>
    <WholesalePrice>1</WholesalePrice>
    <SalePrice>0</SalePrice>
    <OnSale>false</OnSale>
    <Manufacturer>toysmith</Manufacturer>
    <Quantity>23</Quantity>
    <PicturePath>C:\Program Files\SCTech\Voodoo Cash Register\data\inventoryImages\lazerfinger.bmp</PicturePath>
    <DateCreated>2012-02-16T12:54:39.078125-07:00</DateCreated>
  </InventoryItems>
  <InventoryItems>
    <ID>11</ID>
    <categoryID>-1</categoryID>
    <Name>Touch Light Moon</Name>
    <UPC>639277388896</UPC>
    <Price>3.99</Price>
    <WholesalePrice>0</WholesalePrice>
    <SalePrice>0</SalePrice>
    <OnSale>false</OnSale>
    <Quantity>0</Quantity>
    <PicturePath>C:\Program Files\SCTech\Voodoo Cash Register\data\inventoryImages\imageNotAvailable.jpg</PicturePath>
    <DateCreated>2012-02-16T12:55:01.125-07:00</DateCreated>
  </InventoryItems>
  <InventoryItems>
    <ID>12</ID>
    <categoryID>-1</categoryID>
    <Name>Touch Light Moon</Name>
    <UPC>639277388896</UPC>
    <Price>3.99</Price>
    <WholesalePrice>0</WholesalePrice>
    <SalePrice>0</SalePrice>
    <OnSale>false</OnSale>
    <Quantity>1</Quantity>
    <PicturePath>C:\Program Files\SCTech\Voodoo Cash Register\data\inventoryImages\imageNotAvailable.jpg</PicturePath>
    <DateCreated>2012-02-16T12:55:20.90625-07:00</DateCreated>
  </InventoryItems>
  <InventoryItems>
    <ID>13</ID>
    <categoryID>-1</categoryID>
    <Name>Flying Disc</Name>
    <UPC>0639277472977</UPC>
    <Price>3.99</Price>
    <WholesalePrice>1</WholesalePrice>
    <SalePrice>0</SalePrice>
    <OnSale>false</OnSale>
    <Manufacturer>Dollar Tree</Manufacturer>
    <Quantity>3</Quantity>
    <PicturePath>C:\Program Files\SCTech\Voodoo Cash Register\data\inventoryImages\imageNotAvailable.jpg</PicturePath>
    <DateCreated>2012-02-16T12:55:59.734375-07:00</DateCreated>
  </InventoryItems>
  <InventoryItems>
    <ID>14</ID>
    <categoryID>-1</categoryID>
    <Name>Touch Light Moon</Name>
    <UPC>639277388896</UPC>
    <Price>3.99</Price>
    <WholesalePrice>0</WholesalePrice>
    <SalePrice>0</SalePrice>
    <OnSale>false</OnSale>
    <Quantity>0</Quantity>
    <PicturePath>C:\Program Files\SCTech\Voodoo Cash Register\data\inventoryImages\imageNotAvailable.jpg</PicturePath>
    <DateCreated>2012-02-16T12:59:14.640625-07:00</DateCreated>
  </InventoryItems>
  <InventoryItems>
    <ID>15</ID>
    <categoryID>-1</categoryID>
    <Name>Touch Light Star</Name>
    <UPC>639277388896</UPC>
    <Price>3.99</Price>
    <WholesalePrice>0</WholesalePrice>
    <SalePrice>0</SalePrice>
    <OnSale>false</OnSale>
    <Quantity>1</Quantity>
    <PicturePath>C:\Program Files\SCTech\Voodoo Cash Register\data\inventoryImages\imageNotAvailable.jpg</PicturePath>
    <DateCreated>2012-02-16T12:59:23.46875-07:00</DateCreated>
  </InventoryItems>
  <InventoryItems>
    <ID>16</ID>
    <categoryID>-1</categoryID>
    <Name>Puzzle Disney Princess 24 piece </Name>
    <UPC>047754176339</UPC>
    <Price>4.25</Price>
    <WholesalePrice>1</WholesalePrice>
    <SalePrice>0</SalePrice>
    <OnSale>false</OnSale>
    <Manufacturer>dollar tree</Manufacturer>
    <Quantity>2</Quantity>
    <DateCreated>2012-02-16T13:29:45.015625-07:00</DateCreated>
  </InventoryItems>
  <InventoryItems>
    <ID>17</ID>
    <categoryID>-1</categoryID>
    <Name>Puzzle Disney Panarama Jr</Name>
    <UPC>072348504656</UPC>
    <Price>4.25</Price>
    <WholesalePrice>1</WholesalePrice>
    <SalePrice>0</SalePrice>
    <OnSale>false</OnSale>
    <Manufacturer>dollar Tree</Manufacturer>
    <Quantity>1</Quantity>
    <DateCreated>2012-02-16T13:31:04.0625-07:00</DateCreated>
  </InventoryItems>
  <InventoryItems>
    <ID>18</ID>
    <categoryID>-1</categoryID>
    <Name>Shaped Puzzle LPF</Name>
    <UPC>639277209948</UPC>
    <Price>4.25</Price>
    <WholesalePrice>1</WholesalePrice>
    <SalePrice>0</SalePrice>
    <OnSale>false</OnSale>
    <Manufacturer>Dollar Tree</Manufacturer>
    <Quantity>1</Quantity>
    <PicturePath>C:\Program Files\SCTech\Voodoo Cash Register\data\inventoryImages\imageNotAvailable.jpg</PicturePath>
    <DateCreated>2012-02-16T13:31:37.546875-07:00</DateCreated>
  </InventoryItems>
  <InventoryItems>
    <ID>19</ID>
    <categoryID>-1</categoryID>
    <Name>Shaped Puzzle LPF</Name>
    <UPC>639277209948</UPC>
    <Price>4.25</Price>
    <WholesalePrice>1</WholesalePrice>
    <SalePrice>0</SalePrice>
    <OnSale>false</OnSale>
    <Manufacturer>Dollar Tree</Manufacturer>
    <Quantity>1</Quantity>
    <PicturePath>C:\Program Files\SCTech\Voodoo Cash Register\data\inventoryImages\imageNotAvailable.jpg</PicturePath>
    <DateCreated>2012-02-16T13:32:01.640625-07:00</DateCreated>
  </InventoryItems>
  <InventoryItems>
    <ID>20</ID>
    <categoryID>-1</categoryID>
    <Name>Puzzle Mini Town Panoramic</Name>
    <UPC>639277867254</UPC>
    <Price>4.25</Price>
    <WholesalePrice>0</WholesalePrice>
    <SalePrice>0</SalePrice>
    <OnSale>false</OnSale>
    <Quantity>1</Quantity>
    <PicturePath>C:\Program Files\SCTech\Voodoo Cash Register\data\inventoryImages\imageNotAvailable.jpg</PicturePath>
    <DateCreated>2012-02-16T13:33:11.875-07:00</DateCreated>
  </InventoryItems>
  <InventoryItems>
    <ID>21</ID>
    <categoryID>-1</categoryID>
    <Name>Puzzle Star Wars</Name>
    <UPC>639277040893</UPC>
    <Price>3.75</Price>
    <WholesalePrice>0</WholesalePrice>
    <SalePrice>0</SalePrice>
    <OnSale>false</OnSale>
    <Quantity>2</Quantity>
    <PicturePath>C:\Program Files\SCTech\Voodoo Cash Register\data\inventoryImages\imageNotAvailable.jpg</PicturePath>
    <DateCreated>2012-02-16T13:34:18.828125-07:00</DateCreated>
  </InventoryItems>
  <InventoryItems>
    <ID>22</ID>
    <categoryID>-1</categoryID>
    <Name>Puzzle Star Wars</Name>
    <UPC>639277040893</UPC>
    <Price>3.75</Price>
    <WholesalePrice>0</WholesalePrice>
    <SalePrice>0</SalePrice>
    <OnSale>false</OnSale>
    <Quantity>2</Quantity>
    <PicturePath>C:\Program Files\SCTech\Voodoo Cash Register\data\inventoryImages\imageNotAvailable.jpg</PicturePath>
    <DateCreated>2012-02-16T13:34:23.625-07:00</DateCreated>
  </InventoryItems>
  <InventoryItems>
    <ID>23</ID>
    <categoryID>-1</categoryID>
    <Name>Puzzle Star Wars</Name>
    <UPC>639277040893</UPC>
    <Price>3.75</Price>
    <WholesalePrice>0</WholesalePrice>
    <SalePrice>0</SalePrice>
    <OnSale>false</OnSale>
    <Quantity>2</Quantity>
    <PicturePath>C:\Program Files\SCTech\Voodoo Cash Register\data\inventoryImages\imageNotAvailable.jpg</PicturePath>
    <DateCreated>2012-02-16T13:34:43.109375-07:00</DateCreated>
  </InventoryItems>
  <InventoryItems>
    <ID>24</ID>
    <categoryID>-1</categoryID>
    <Name>Puzzle Disney Panarama Jr</Name>
    <UPC>072348504656</UPC>
    <Price>4.25</Price>
    <WholesalePrice>1</WholesalePrice>
    <SalePrice>0</SalePrice>
    <OnSale>false</OnSale>
    <Manufacturer>dollar Tree</Manufacturer>
    <Quantity>1</Quantity>
    <PicturePath>C:\Program Files\SCTech\Voodoo Cash Register\data\inventoryImages\imageNotAvailable.jpg</PicturePath>
    <DateCreated>2012-02-16T13:35:18.890625-07:00</DateCreated>
  </InventoryItems>
  <InventoryItems>
    <ID>25</ID>
    <categoryID>-1</categoryID>
    <Name>Puzzle Disney Princess 24 piece </Name>
    <UPC>047754176339</UPC>
    <Price>4.25</Price>
    <WholesalePrice>1</WholesalePrice>
    <SalePrice>0</SalePrice>
    <OnSale>false</OnSale>
    <Manufacturer>dollar tree</Manufacturer>
    <Quantity>2</Quantity>
    <PicturePath>C:\Program Files\SCTech\Voodoo Cash Register\data\inventoryImages\imageNotAvailable.jpg</PicturePath>
    <DateCreated>2012-02-16T13:35:43.15625-07:00</DateCreated>
  </InventoryItems>
  <InventoryItems>
    <ID>26</ID>
    <categoryID>-1</categoryID>
    <Name>robot 3-D puzzle</Name>
    <UPC>400100930809</UPC>
    <Price>2.99</Price>
    <WholesalePrice>0</WholesalePrice>
    <SalePrice>0</SalePrice>
    <OnSale>false</OnSale>
    <Quantity>2</Quantity>
    <DateCreated>2012-02-16T16:06:23.28125-07:00</DateCreated>
  </InventoryItems>
  <InventoryItems>
    <ID>27</ID>
    <categoryID>-1</categoryID>
    <Name>Robot 3-D puzzle</Name>
    <UPC>400100930809</UPC>
    <Price>2.99</Price>
    <WholesalePrice>0</WholesalePrice>
    <SalePrice>0</SalePrice>
    <OnSale>false</OnSale>
    <Quantity>2</Quantity>
    <PicturePath>C:\Program Files\SCTech\Voodoo Cash Register\data\inventoryImages\imageNotAvailable.jpg</PicturePath>
    <DateCreated>2012-02-16T16:06:51.25-07:00</DateCreated>
  </InventoryItems>
  <InventoryItems>
    <ID>28</ID>
    <categoryID>-1</categoryID>
    <Name>Robot 3-D puzzle</Name>
    <UPC>400100930809</UPC>
    <Price>2.99</Price>
    <WholesalePrice>0</WholesalePrice>
    <SalePrice>0</SalePrice>
    <OnSale>false</OnSale>
    <Quantity>2</Quantity>
    <PicturePath>C:\Program Files\SCTech\Voodoo Cash Register\data\inventoryImages\imageNotAvailable.jpg</PicturePath>
    <DateCreated>2012-02-16T16:07:11.703125-07:00</DateCreated>
  </InventoryItems>
  <InventoryItems>
    <ID>29</ID>
    <categoryID>-1</categoryID>
    <Name>Kids Scissors</Name>
    <UPC>078484088036</UPC>
    <Price>2.99</Price>
    <WholesalePrice>0</WholesalePrice>
    <SalePrice>0</SalePrice>
    <OnSale>false</OnSale>
    <Quantity>2</Quantity>
    <DateCreated>2012-02-16T16:08:05.15625-07:00</DateCreated>
  </InventoryItems>
  <InventoryItems>
    <ID>30</ID>
    <categoryID>-1</categoryID>
    <Name>Kids Scissors</Name>
    <UPC>078484088036</UPC>
    <Price>2.99</Price>
    <WholesalePrice>0</WholesalePrice>
    <SalePrice>0</SalePrice>
    <OnSale>false</OnSale>
    <Quantity>2</Quantity>
    <PicturePath>C:\Program Files\SCTech\Voodoo Cash Register\data\inventoryImages\imageNotAvailable.jpg</PicturePath>
    <DateCreated>2012-02-16T16:08:24.015625-07:00</DateCreated>
  </InventoryItems>
  <InventoryItems>
    <ID>31</ID>
    <categoryID>-1</categoryID>
    <Name>Dollhouse Kit</Name>
    <UPC>0639277200099</UPC>
    <Price>5.99</Price>
    <WholesalePrice>1</WholesalePrice>
    <SalePrice>0</SalePrice>
    <OnSale>false</OnSale>
    <Manufacturer>Dollar Tree</Manufacturer>
    <Quantity>2</Quantity>
    <PicturePath>C:\Program Files\SCTech\Voodoo Cash Register\data\inventoryImages\imageNotAvailable.jpg</PicturePath>
    <DateCreated>2012-02-16T16:09:47.015625-07:00</DateCreated>
  </InventoryItems>
  <InventoryItems>
    <ID>32</ID>
    <categoryID>-1</categoryID>
    <Name>Crayola Crayons</Name>
    <Description>Set of 16 Crayola Crayons. Classic colors. #1 brand preferred by teachers. Nontoxic.</Description>
    <UPC>0716620772660</UPC>
    <Price>2.5</Price>
    <WholesalePrice>1.25</WholesalePrice>
    <SalePrice>0</SalePrice>
    <OnSale>false</OnSale>
    <Manufacturer>Ben International</Manufacturer>
    <Quantity>12</Quantity>
    <PicturePath>C:\Program Files\SCTech\Voodoo Cash Register\data\inventoryImages\imageNotAvailable.jpg</PicturePath>
    <DateCreated>2012-02-16T16:10:30.34375-07:00</DateCreated>
  </InventoryItems>
  <InventoryItems>
    <ID>33</ID>
    <categoryID>-1</categoryID>
    <Name>Crayola Markers</Name>
    <Description>Set of 10 fine line classic colors Crayola Markers. Made with recycled plastic and solar energy. #1 brand preferred by teachers</Description>
    <UPC>071662077266</UPC>
    <Price>4.75</Price>
    <WholesalePrice>2.3</WholesalePrice>
    <SalePrice>0</SalePrice>
    <OnSale>false</OnSale>
    <Manufacturer>Ben International</Manufacturer>
    <Quantity>5</Quantity>
    <PicturePath>C:\Program Files\SCTech\Voodoo Cash Register\data\inventoryImages\imageNotAvailable.jpg</PicturePath>
    <DateCreated>2012-02-16T16:10:51.78125-07:00</DateCreated>
  </InventoryItems>
  <InventoryItems>
    <ID>34</ID>
    <categoryID>-1</categoryID>
    <Name>Stickers - 500</Name>
    <UPC>0639277049377</UPC>
    <Price>3.25</Price>
    <WholesalePrice>1</WholesalePrice>
    <SalePrice>0</SalePrice>
    <OnSale>false</OnSale>
    <Manufacturer>DollarTree</Manufacturer>
    <Quantity>2</Quantity>
    <PicturePath>C:\Program Files\SCTech\Voodoo Cash Register\data\inventoryImages\imageNotAvailable.jpg</PicturePath>
    <DateCreated>2012-02-16T16:13:06.78125-07:00</DateCreated>
  </InventoryItems>
  <InventoryItems>
    <ID>35</ID>
    <categoryID>-1</categoryID>
    <Name>Stickers - 500</Name>
    <UPC>0639277049377</UPC>
    <Price>3.25</Price>
    <WholesalePrice>1</WholesalePrice>
    <SalePrice>0</SalePrice>
    <OnSale>false</OnSale>
    <Manufacturer>DollarTree</Manufacturer>
    <Quantity>2</Quantity>
    <PicturePath>C:\Program Files\SCTech\Voodoo Cash Register\data\inventoryImages\imageNotAvailable.jpg</PicturePath>
    <DateCreated>2012-02-16T16:13:36.234375-07:00</DateCreated>
  </InventoryItems>
  <InventoryItems>
    <ID>36</ID>
    <categoryID>-1</categoryID>
    <Name>Stickers - 500</Name>
    <UPC>0639277049377</UPC>
    <Price>3.25</Price>
    <WholesalePrice>1</WholesalePrice>
    <SalePrice>0</SalePrice>
    <OnSale>false</OnSale>
    <Manufacturer>DollarTree</Manufacturer>
    <Quantity>6</Quantity>
    <PicturePath>C:\Program Files\SCTech\Voodoo Cash Register\data\inventoryImages\imageNotAvailable.jpg</PicturePath>
    <DateCreated>2012-02-16T16:13:46.796875-07:00</DateCreated>
  </InventoryItems>
  <InventoryItems>
    <ID>37</ID>
    <categoryID>-1</categoryID>
    <Name>Puzzle Mini Town Panoramic</Name>
    <UPC>639277867254</UPC>
    <Price>4.25</Price>
    <WholesalePrice>0</WholesalePrice>
    <SalePrice>0</SalePrice>
    <OnSale>false</OnSale>
    <Quantity>3</Quantity>
    <PicturePath>C:\Program Files\SCTech\Voodoo Cash Register\data\inventoryImages\imageNotAvailable.jpg</PicturePath>
    <DateCreated>2012-02-16T16:14:29.1875-07:00</DateCreated>
  </InventoryItems>
  <InventoryItems>
    <ID>38</ID>
    <categoryID>-1</categoryID>
    <Name>Puzzle Mini Town Panoramic</Name>
    <UPC>639277867254</UPC>
    <Price>4.25</Price>
    <WholesalePrice>0</WholesalePrice>
    <SalePrice>0</SalePrice>
    <OnSale>false</OnSale>
    <Quantity>3</Quantity>
    <PicturePath>C:\Program Files\SCTech\Voodoo Cash Register\data\inventoryImages\imageNotAvailable.jpg</PicturePath>
    <DateCreated>2012-02-16T16:14:50.390625-07:00</DateCreated>
  </InventoryItems>
  <InventoryItems>
    <ID>39</ID>
    <categoryID>-1</categoryID>
    <Name>Animal Puppet</Name>
    <UPC>639277867513</UPC>
    <Price>4.5</Price>
    <WholesalePrice>1</WholesalePrice>
    <SalePrice>0</SalePrice>
    <OnSale>false</OnSale>
    <Manufacturer>Dollar Tree</Manufacturer>
    <Quantity>1</Quantity>
    <PicturePath>C:\Program Files\SCTech\Voodoo Cash Register\data\inventoryImages\imageNotAvailable.jpg</PicturePath>
    <DateCreated>2012-02-16T16:15:17-07:00</DateCreated>
  </InventoryItems>
  <InventoryItems>
    <ID>40</ID>
    <categoryID>-1</categoryID>
    <Name>Crayon Rings</Name>
    <UPC>639277214119</UPC>
    <Price>1.99</Price>
    <WholesalePrice>1</WholesalePrice>
    <SalePrice>0</SalePrice>
    <OnSale>false</OnSale>
    <Manufacturer>Dollar Tree</Manufacturer>
    <Quantity>1</Quantity>
    <PicturePath>C:\Program Files\SCTech\Voodoo Cash Register\data\inventoryImages\imageNotAvailable.jpg</PicturePath>
    <DateCreated>2012-02-16T16:15:49.625-07:00</DateCreated>
  </InventoryItems>
  <InventoryItems>
    <ID>41</ID>
    <categoryID>-1</categoryID>
    <Name>Crayon Rings</Name>
    <UPC>639277214119</UPC>
    <Price>1.99</Price>
    <WholesalePrice>1</WholesalePrice>
    <SalePrice>0</SalePrice>
    <OnSale>false</OnSale>
    <Manufacturer>Dollar Tree</Manufacturer>
    <Quantity>1</Quantity>
    <PicturePath>C:\Program Files\SCTech\Voodoo Cash Register\data\inventoryImages\imageNotAvailable.jpg</PicturePath>
    <DateCreated>2012-02-16T16:16:04.515625-07:00</DateCreated>
  </InventoryItems>
  <InventoryItems>
    <ID>42</ID>
    <categoryID>-1</categoryID>
    <Name>Gigantic Coloring Books with Stickers</Name>
    <UPC>639277823212</UPC>
    <Price>5.99</Price>
    <WholesalePrice>1</WholesalePrice>
    <SalePrice>0</SalePrice>
    <OnSale>false</OnSale>
    <Manufacturer>dollar tree</Manufacturer>
    <Quantity>4</Quantity>
    <DateCreated>2012-02-16T16:18:28.546875-07:00</DateCreated>
  </InventoryItems>
  <InventoryItems>
    <ID>43</ID>
    <categoryID>-1</categoryID>
    <Name>Gigantic Coloring Books with Stickers</Name>
    <UPC>639277823212</UPC>
    <Price>5.99</Price>
    <WholesalePrice>1</WholesalePrice>
    <SalePrice>0</SalePrice>
    <OnSale>false</OnSale>
    <Manufacturer>dollar tree</Manufacturer>
    <Quantity>4</Quantity>
    <PicturePath>C:\Program Files\SCTech\Voodoo Cash Register\data\inventoryImages\imageNotAvailable.jpg</PicturePath>
    <DateCreated>2012-02-16T16:18:46.75-07:00</DateCreated>
  </InventoryItems>
  <InventoryItems>
    <ID>44</ID>
    <categoryID>-1</categoryID>
    <Name>Puzzle Disney Cars</Name>
    <UPC>047754266320</UPC>
    <Price>4.25</Price>
    <WholesalePrice>1</WholesalePrice>
    <SalePrice>0</SalePrice>
    <OnSale>false</OnSale>
    <Manufacturer>dollar tree</Manufacturer>
    <Quantity>1</Quantity>
    <DateCreated>2012-02-16T16:20:32.5625-07:00</DateCreated>
  </InventoryItems>
  <InventoryItems>
    <ID>45</ID>
    <categoryID>-1</categoryID>
    <Name>Puzzle Disney Cars</Name>
    <UPC>047754266320</UPC>
    <Price>4.25</Price>
    <WholesalePrice>1</WholesalePrice>
    <SalePrice>0</SalePrice>
    <OnSale>false</OnSale>
    <Manufacturer>dollar tree</Manufacturer>
    <Quantity>1</Quantity>
    <PicturePath>C:\Program Files\SCTech\Voodoo Cash Register\data\inventoryImages\imageNotAvailable.jpg</PicturePath>
    <DateCreated>2012-02-16T16:21:15.453125-07:00</DateCreated>
  </InventoryItems>
  <InventoryItems>
    <ID>46</ID>
    <categoryID>-1</categoryID>
    <Name>Puzzle Spider-Man</Name>
    <UPC>047754565348</UPC>
    <Price>4.25</Price>
    <WholesalePrice>1</WholesalePrice>
    <SalePrice>0</SalePrice>
    <OnSale>false</OnSale>
    <Manufacturer>dollar tree</Manufacturer>
    <Quantity>1</Quantity>
    <DateCreated>2012-02-16T16:22:35.53125-07:00</DateCreated>
  </InventoryItems>
  <InventoryItems>
    <ID>47</ID>
    <categoryID>-1</categoryID>
    <Name>Puzzle Spider-Man</Name>
    <UPC>047754565348</UPC>
    <Price>4.25</Price>
    <WholesalePrice>1</WholesalePrice>
    <SalePrice>0</SalePrice>
    <OnSale>false</OnSale>
    <Manufacturer>dollar tree</Manufacturer>
    <Quantity>1</Quantity>
    <PicturePath>C:\Program Files\SCTech\Voodoo Cash Register\data\inventoryImages\imageNotAvailable.jpg</PicturePath>
    <DateCreated>2012-02-16T16:22:48.8125-07:00</DateCreated>
  </InventoryItems>
  <InventoryItems>
    <ID>48</ID>
    <categoryID>-1</categoryID>
    <Name>Stickers - 500</Name>
    <UPC>0639277049377</UPC>
    <Price>3.25</Price>
    <WholesalePrice>1</WholesalePrice>
    <SalePrice>0</SalePrice>
    <OnSale>false</OnSale>
    <Manufacturer>DollarTree</Manufacturer>
    <Quantity>5</Quantity>
    <PicturePath>C:\Program Files\SCTech\Voodoo Cash Register\data\inventoryImages\imageNotAvailable.jpg</PicturePath>
    <DateCreated>2012-02-16T16:29:16.109375-07:00</DateCreated>
  </InventoryItems>
  <InventoryItems>
    <ID>49</ID>
    <categoryID>-1</categoryID>
    <Name>Dark Ascension Intro Deck</Name>
    <UPC>653569695356</UPC>
    <Price>13.99</Price>
    <WholesalePrice>7.4</WholesalePrice>
    <SalePrice>0</SalePrice>
    <OnSale>false</OnSale>
    <Manufacturer>Southern Hobby</Manufacturer>
    <Quantity>9</Quantity>
    <PicturePath>C:\Program Files\SCTech\Voodoo Cash Register\data\inventoryImages\DarkAscensionIntroDeck.jpg</PicturePath>
    <DateCreated>2012-02-16T17:35:50.484375-07:00</DateCreated>
  </InventoryItems>
  <InventoryItems>
    <ID>50</ID>
    <categoryID>-1</categoryID>
    <Name>Card Protector sleeves - Black</Name>
    <UPC>074427826697</UPC>
    <Price>2.99</Price>
    <WholesalePrice>1.7</WholesalePrice>
    <SalePrice>0</SalePrice>
    <OnSale>false</OnSale>
    <Quantity>3</Quantity>
    <PicturePath>C:\Program Files\SCTech\Voodoo Cash Register\data\inventoryImages\imageNotAvailable.jpg</PicturePath>
    <DateCreated>2012-02-16T17:38:29.984375-07:00</DateCreated>
  </InventoryItems>
</NewDataSet>