<?xml version="1.0" standalone="yes"?>
<NewDataSet>
  <InventoryItems>
    <ID>0</ID>
    <Name>New Cart_12:05 PM</Name>
    <Description>Cash Transaction</Description>
    <UPC />
    <Price>0</Price>
    <WholesalePrice>0</WholesalePrice>
    <SalePrice>0</SalePrice>
    <OnSale>false</OnSale>
    <Manufacturer />
    <Model />
    <Size />
    <Color />
    <Quantity>0</Quantity>
    <picturePath />
    <status />
    <DateCreated>2011-12-05T12:05:52.625-07:00</DateCreated>
  </InventoryItems>
  <InventoryItems>
    <ID>0</ID>
    <Name>New Cart_2:17 PM</Name>
    <Description>Credit Transaction</Description>
    <UPC />
    <Price>0</Price>
    <WholesalePrice>0</WholesalePrice>
    <SalePrice>0</SalePrice>
    <OnSale>false</OnSale>
    <Manufacturer />
    <Model />
    <Size />
    <Color />
    <Quantity>0</Quantity>
    <picturePath />
    <status />
    <DateCreated>2011-12-05T14:17:47.21875-07:00</DateCreated>
  </InventoryItems>
  <InventoryItems>
    <ID>0</ID>
    <Name>New Cart_12:05 PM</Name>
    <Description>Cash Transaction</Description>
    <UPC />
    <Price>0</Price>
    <WholesalePrice>0</WholesalePrice>
    <SalePrice>0</SalePrice>
    <OnSale>false</OnSale>
    <Manufacturer />
    <Model />
    <Size />
    <Color />
    <Quantity>0</Quantity>
    <picturePath />
    <status />
    <DateCreated>2011-12-05T14:17:47.25-07:00</DateCreated>
  </InventoryItems>
  <InventoryItems>
    <ID>17</ID>
    <Name>Rubber band shooter</Name>
    <Description />
    <UPC>0085761025288</UPC>
    <Price>12.95</Price>
    <WholesalePrice>0</WholesalePrice>
    <SalePrice>0</SalePrice>
    <OnSale>true</OnSale>
    <Manufacturer />
    <Model />
    <Size />
    <Color />
    <Quantity>1</Quantity>
    <picturePath>C:\Program Files\SCTech\Voodoo Cash Register\data\inventoryImages\imageNotAvailable.jpg</picturePath>
    <status />
    <DateCreated>2011-12-05T14:17:47.265625-07:00</DateCreated>
  </InventoryItems>
  <InventoryItems>
    <ID>23</ID>
    <Name>X Stream Internal Wing Aircraft</Name>
    <Description />
    <UPC>0085761077683</UPC>
    <Price>6.75</Price>
    <WholesalePrice>0</WholesalePrice>
    <SalePrice>0</SalePrice>
    <OnSale>true</OnSale>
    <Manufacturer />
    <Model />
    <Size />
    <Color />
    <Quantity>1</Quantity>
    <picturePath>C:\Program Files\SCTech\Voodoo Cash Register\data\inventoryImages\imageNotAvailable.jpg</picturePath>
    <status />
    <DateCreated>2011-12-05T14:17:47.265625-07:00</DateCreated>
  </InventoryItems>
  <InventoryItems>
    <ID>93</ID>
    <Name>Firefly</Name>
    <Description />
    <UPC>665766081207</UPC>
    <Price>4.75</Price>
    <WholesalePrice>0</WholesalePrice>
    <SalePrice>0</SalePrice>
    <OnSale>true</OnSale>
    <Manufacturer />
    <Model />
    <Size />
    <Color />
    <Quantity>1</Quantity>
    <picturePath>C:\Program Files\SCTech\Voodoo Cash Register\data\inventoryImages\imageNotAvailable.jpg</picturePath>
    <status />
    <DateCreated>2011-12-05T14:17:47.28125-07:00</DateCreated>
  </InventoryItems>
  <InventoryItems>
    <ID>171</ID>
    <Name>Mary's Soft Dough Tutti Frutti</Name>
    <Description />
    <UPC />
    <Price>2.5</Price>
    <WholesalePrice>0</WholesalePrice>
    <SalePrice>0</SalePrice>
    <OnSale>true</OnSale>
    <Manufacturer />
    <Model />
    <Size />
    <Color />
    <Quantity>1</Quantity>
    <picturePath>C:\Program Files\SCTech\Voodoo Cash Register\data\inventoryImages\imageNotAvailable.jpg</picturePath>
    <status />
    <DateCreated>2011-12-05T14:17:47.28125-07:00</DateCreated>
  </InventoryItems>
  <InventoryItems>
    <ID>0</ID>
    <Name>New Cart_4:07 PM</Name>
    <Description>Credit Transaction</Description>
    <UPC />
    <Price>0</Price>
    <WholesalePrice>0</WholesalePrice>
    <SalePrice>0</SalePrice>
    <OnSale>false</OnSale>
    <Manufacturer />
    <Model />
    <Size />
    <Color />
    <Quantity>0</Quantity>
    <picturePath />
    <status />
    <DateCreated>2011-12-05T16:07:35.421875-07:00</DateCreated>
  </InventoryItems>
  <InventoryItems>
    <ID>97</ID>
    <Name>Cosmic Thruster</Name>
    <Description />
    <UPC>085761052994</UPC>
    <Price>24.95</Price>
    <WholesalePrice>0</WholesalePrice>
    <SalePrice>0</SalePrice>
    <OnSale>true</OnSale>
    <Manufacturer />
    <Model />
    <Size />
    <Color />
    <Quantity>1</Quantity>
    <picturePath>C:\Program Files\SCTech\Voodoo Cash Register\data\inventoryImages\imageNotAvailable.jpg</picturePath>
    <status />
    <DateCreated>2011-12-05T16:07:35.4375-07:00</DateCreated>
  </InventoryItems>
  <InventoryItems>
    <ID>20</ID>
    <Name>Plasma Orb Light</Name>
    <Description />
    <UPC>085761037038</UPC>
    <Price>19.95</Price>
    <WholesalePrice>0</WholesalePrice>
    <SalePrice>0</SalePrice>
    <OnSale>true</OnSale>
    <Manufacturer />
    <Model />
    <Size />
    <Color />
    <Quantity>1</Quantity>
    <picturePath>C:\Program Files\SCTech\Voodoo Cash Register\data\inventoryImages\imageNotAvailable.jpg</picturePath>
    <status />
    <DateCreated>2011-12-05T16:07:35.453125-07:00</DateCreated>
  </InventoryItems>
  <InventoryItems>
    <ID>185</ID>
    <Name>Mary's Soft Dough Tool Set</Name>
    <Description />
    <UPC />
    <Price>7.99</Price>
    <WholesalePrice>0</WholesalePrice>
    <SalePrice>0</SalePrice>
    <OnSale>true</OnSale>
    <Manufacturer />
    <Model />
    <Size />
    <Color />
    <Quantity>1</Quantity>
    <picturePath>C:\Program Files\SCTech\Voodoo Cash Register\data\inventoryImages\imageNotAvailable.jpg</picturePath>
    <status />
    <DateCreated>2011-12-05T16:07:35.453125-07:00</DateCreated>
  </InventoryItems>
  <InventoryItems>
    <ID>18</ID>
    <Name>Snuggle Baby</Name>
    <Description />
    <UPC>0085761121027</UPC>
    <Price>7.65</Price>
    <WholesalePrice>0</WholesalePrice>
    <SalePrice>0</SalePrice>
    <OnSale>true</OnSale>
    <Manufacturer />
    <Model />
    <Size />
    <Color />
    <Quantity>1</Quantity>
    <picturePath>C:\Program Files\SCTech\Voodoo Cash Register\data\inventoryImages\imageNotAvailable.jpg</picturePath>
    <status />
    <DateCreated>2011-12-05T16:07:35.46875-07:00</DateCreated>
  </InventoryItems>
  <InventoryItems>
    <ID>114</ID>
    <Name>Blast Bow</Name>
    <Description />
    <UPC>085761015357</UPC>
    <Price>24.95</Price>
    <WholesalePrice>0</WholesalePrice>
    <SalePrice>0</SalePrice>
    <OnSale>true</OnSale>
    <Manufacturer />
    <Model />
    <Size />
    <Color />
    <Quantity>1</Quantity>
    <picturePath>C:\Program Files\SCTech\Voodoo Cash Register\data\inventoryImages\imageNotAvailable.jpg</picturePath>
    <status />
    <DateCreated>2011-12-05T16:07:35.5-07:00</DateCreated>
  </InventoryItems>
  <InventoryItems>
    <ID>168</ID>
    <Name>Mary's Soft Dough Chocolate</Name>
    <Description />
    <UPC />
    <Price>2.5</Price>
    <WholesalePrice>0</WholesalePrice>
    <SalePrice>0</SalePrice>
    <OnSale>true</OnSale>
    <Manufacturer />
    <Model />
    <Size />
    <Color />
    <Quantity>1</Quantity>
    <picturePath>C:\Program Files\SCTech\Voodoo Cash Register\data\inventoryImages\imageNotAvailable.jpg</picturePath>
    <status />
    <DateCreated>2011-12-05T16:07:35.53125-07:00</DateCreated>
  </InventoryItems>
  <InventoryItems>
    <ID>183</ID>
    <Name>Mary's Soft Dough Grape</Name>
    <Description />
    <UPC />
    <Price>2.5</Price>
    <WholesalePrice>0</WholesalePrice>
    <SalePrice>0</SalePrice>
    <OnSale>true</OnSale>
    <Manufacturer />
    <Model />
    <Size />
    <Color />
    <Quantity>1</Quantity>
    <picturePath>C:\Program Files\SCTech\Voodoo Cash Register\data\inventoryImages\imageNotAvailable.jpg</picturePath>
    <status />
    <DateCreated>2011-12-05T16:07:35.53125-07:00</DateCreated>
  </InventoryItems>
  <InventoryItems>
    <ID>171</ID>
    <Name>Mary's Soft Dough Tutti Frutti</Name>
    <Description />
    <UPC />
    <Price>2.5</Price>
    <WholesalePrice>0</WholesalePrice>
    <SalePrice>0</SalePrice>
    <OnSale>true</OnSale>
    <Manufacturer />
    <Model />
    <Size />
    <Color />
    <Quantity>1</Quantity>
    <picturePath>C:\Program Files\SCTech\Voodoo Cash Register\data\inventoryImages\imageNotAvailable.jpg</picturePath>
    <status />
    <DateCreated>2011-12-05T16:07:35.546875-07:00</DateCreated>
  </InventoryItems>
  <InventoryItems>
    <ID>170</ID>
    <Name>Mary's Soft Dough Orange</Name>
    <Description />
    <UPC />
    <Price>2.5</Price>
    <WholesalePrice>0</WholesalePrice>
    <SalePrice>0</SalePrice>
    <OnSale>true</OnSale>
    <Manufacturer />
    <Model />
    <Size />
    <Color />
    <Quantity>1</Quantity>
    <picturePath>C:\Program Files\SCTech\Voodoo Cash Register\data\inventoryImages\imageNotAvailable.jpg</picturePath>
    <status />
    <DateCreated>2011-12-05T16:07:35.5625-07:00</DateCreated>
  </InventoryItems>
  <InventoryItems>
    <ID>0</ID>
    <Name>New Cart_4:16 PM</Name>
    <Description>Cash Transaction</Description>
    <UPC />
    <Price>0</Price>
    <WholesalePrice>0</WholesalePrice>
    <SalePrice>0</SalePrice>
    <OnSale>false</OnSale>
    <Manufacturer />
    <Model />
    <Size />
    <Color />
    <Quantity>0</Quantity>
    <picturePath />
    <status />
    <DateCreated>2011-12-05T16:16:34.0625-07:00</DateCreated>
  </InventoryItems>
  <InventoryItems>
    <ID>0</ID>
    <Name>New Cart_4:27 PM</Name>
    <Description>Cash Transaction</Description>
    <UPC />
    <Price>0</Price>
    <WholesalePrice>0</WholesalePrice>
    <SalePrice>0</SalePrice>
    <OnSale>false</OnSale>
    <Manufacturer />
    <Model />
    <Size />
    <Color />
    <Quantity>0</Quantity>
    <picturePath />
    <status />
    <DateCreated>2011-12-05T16:27:07.484375-07:00</DateCreated>
  </InventoryItems>
  <InventoryItems>
    <ID>0</ID>
    <Name>New Cart_4:16 PM</Name>
    <Description>Cash Transaction</Description>
    <UPC />
    <Price>0</Price>
    <WholesalePrice>0</WholesalePrice>
    <SalePrice>0</SalePrice>
    <OnSale>false</OnSale>
    <Manufacturer />
    <Model />
    <Size />
    <Color />
    <Quantity>0</Quantity>
    <picturePath />
    <status />
    <DateCreated>2011-12-05T16:27:07.5-07:00</DateCreated>
  </InventoryItems>
  <InventoryItems>
    <ID>0</ID>
    <Name>New Cart_4:33 PM</Name>
    <Description>Cash Transaction</Description>
    <UPC />
    <Price>0</Price>
    <WholesalePrice>0</WholesalePrice>
    <SalePrice>0</SalePrice>
    <OnSale>false</OnSale>
    <Manufacturer />
    <Model />
    <Size />
    <Color />
    <Quantity>0</Quantity>
    <picturePath />
    <status />
    <DateCreated>2011-12-05T16:33:47.046875-07:00</DateCreated>
  </InventoryItems>
  <InventoryItems>
    <ID>0</ID>
    <Name>New Cart_4:27 PM</Name>
    <Description>Cash Transaction</Description>
    <UPC />
    <Price>0</Price>
    <WholesalePrice>0</WholesalePrice>
    <SalePrice>0</SalePrice>
    <OnSale>false</OnSale>
    <Manufacturer />
    <Model />
    <Size />
    <Color />
    <Quantity>0</Quantity>
    <picturePath />
    <status />
    <DateCreated>2011-12-05T16:33:47.0625-07:00</DateCreated>
  </InventoryItems>
  <InventoryItems>
    <ID>0</ID>
    <Name>New Cart_4:16 PM</Name>
    <Description>Cash Transaction</Description>
    <UPC />
    <Price>0</Price>
    <WholesalePrice>0</WholesalePrice>
    <SalePrice>0</SalePrice>
    <OnSale>false</OnSale>
    <Manufacturer />
    <Model />
    <Size />
    <Color />
    <Quantity>0</Quantity>
    <picturePath />
    <status />
    <DateCreated>2011-12-05T16:33:47.078125-07:00</DateCreated>
  </InventoryItems>
  <InventoryItems>
    <ID>122</ID>
    <Name>Mini Burger</Name>
    <Description />
    <UPC />
    <Price>0.5</Price>
    <WholesalePrice>0</WholesalePrice>
    <SalePrice>0</SalePrice>
    <OnSale>true</OnSale>
    <Manufacturer />
    <Model />
    <Size />
    <Color />
    <Quantity>1</Quantity>
    <picturePath>C:\Program Files\SCTech\Voodoo Cash Register\data\inventoryImages\imageNotAvailable.jpg</picturePath>
    <status />
    <DateCreated>2011-12-05T16:33:47.078125-07:00</DateCreated>
  </InventoryItems>
  <InventoryItems>
    <ID>0</ID>
    <Name>New Cart_4:35 PM</Name>
    <Description>Cash Transaction</Description>
    <UPC />
    <Price>0</Price>
    <WholesalePrice>0</WholesalePrice>
    <SalePrice>0</SalePrice>
    <OnSale>false</OnSale>
    <Manufacturer />
    <Model />
    <Size />
    <Color />
    <Quantity>0</Quantity>
    <picturePath />
    <status />
    <DateCreated>2011-12-05T16:35:22.453125-07:00</DateCreated>
  </InventoryItems>
  <InventoryItems>
    <ID>0</ID>
    <Name>New Cart_4:49 PM</Name>
    <Description>Cash Transaction</Description>
    <UPC />
    <Price>0</Price>
    <WholesalePrice>0</WholesalePrice>
    <SalePrice>0</SalePrice>
    <OnSale>false</OnSale>
    <Manufacturer />
    <Model />
    <Size />
    <Color />
    <Quantity>0</Quantity>
    <picturePath />
    <status />
    <DateCreated>2011-12-05T16:49:33.0625-07:00</DateCreated>
  </InventoryItems>
  <InventoryItems>
    <ID>0</ID>
    <Name>New Cart_5:29 PM</Name>
    <Description>Credit Transaction</Description>
    <UPC />
    <Price>0</Price>
    <WholesalePrice>0</WholesalePrice>
    <SalePrice>0</SalePrice>
    <OnSale>false</OnSale>
    <Manufacturer />
    <Model />
    <Size />
    <Color />
    <Quantity>0</Quantity>
    <picturePath />
    <status />
    <DateCreated>2011-12-05T17:29:36.5-07:00</DateCreated>
  </InventoryItems>
  <InventoryItems>
    <ID>0</ID>
    <Name>New Cart_4:49 PM</Name>
    <Description>Cash Transaction</Description>
    <UPC />
    <Price>0</Price>
    <WholesalePrice>0</WholesalePrice>
    <SalePrice>0</SalePrice>
    <OnSale>false</OnSale>
    <Manufacturer />
    <Model />
    <Size />
    <Color />
    <Quantity>0</Quantity>
    <picturePath />
    <status />
    <DateCreated>2011-12-05T17:29:36.515625-07:00</DateCreated>
  </InventoryItems>
  <InventoryItems>
    <ID>125</ID>
    <Name>Mini Puzzle</Name>
    <Description />
    <UPC />
    <Price>6.25</Price>
    <WholesalePrice>0</WholesalePrice>
    <SalePrice>0</SalePrice>
    <OnSale>true</OnSale>
    <Manufacturer />
    <Model />
    <Size />
    <Color />
    <Quantity>2</Quantity>
    <picturePath>C:\Program Files\SCTech\Voodoo Cash Register\data\inventoryImages\imageNotAvailable.jpg</picturePath>
    <status />
    <DateCreated>2011-12-05T17:29:36.515625-07:00</DateCreated>
  </InventoryItems>
</NewDataSet>