<?xml version="1.0" standalone="yes"?>
<NewDataSet>
  <InventoryItems>
    <ID>1</ID>
    <categoryID>-1</categoryID>
    <Name>New Cart_4:04 PM</Name>
    <Description>Cash Transaction</Description>
    <Price>8.96</Price>
    <WholesalePrice>0</WholesalePrice>
    <SalePrice>0</SalePrice>
    <OnSale>false</OnSale>
    <Quantity>0</Quantity>
    <active>true</active>
    <displayOnWeb>true</displayOnWeb>
    <DateCreated>2012-10-06T16:05:00.03125-06:00</DateCreated>
  </InventoryItems>
  <InventoryItems>
    <ID>2</ID>
    <categoryID>-1</categoryID>
    <Name>Magic New Phyrexia</Name>
    <UPC>653569596301</UPC>
    <Price>7.25</Price>
    <WholesalePrice>0</WholesalePrice>
    <SalePrice>0</SalePrice>
    <OnSale>false</OnSale>
    <Quantity>1</Quantity>
    <picturePath>C:\Program Files\SCTech\Voodoo Cash Register\data\inventoryImages\imageNotAvailable.jpg</picturePath>
    <active>true</active>
    <displayOnWeb>true</displayOnWeb>
    <DateCreated>2012-10-06T16:05:00.765625-06:00</DateCreated>
  </InventoryItems>
  <InventoryItems>
    <ID>3</ID>
    <categoryID>-1</categoryID>
    <Price>0.5</Price>
    <WholesalePrice>0</WholesalePrice>
    <SalePrice>0</SalePrice>
    <OnSale>false</OnSale>
    <Quantity>2</Quantity>
    <active>true</active>
    <displayOnWeb>true</displayOnWeb>
    <DateCreated>2012-10-06T16:05:04.796875-06:00</DateCreated>
  </InventoryItems>
  <InventoryItems>
    <ID>4</ID>
    <categoryID>-1</categoryID>
    <Name>New Cart_4:13 PM</Name>
    <Description>Cash for 16.00 and Credit Transaction for -13.30</Description>
    <Price>29.3</Price>
    <WholesalePrice>0</WholesalePrice>
    <SalePrice>0</SalePrice>
    <OnSale>false</OnSale>
    <Quantity>0</Quantity>
    <active>true</active>
    <displayOnWeb>true</displayOnWeb>
    <DateCreated>2012-10-06T16:13:01.03125-06:00</DateCreated>
  </InventoryItems>
  <InventoryItems>
    <ID>5</ID>
    <categoryID>-1</categoryID>
    <Name>Nerf N strike Maverick Sonic Series</Name>
    <UPC>653569579557</UPC>
    <Price>26.99</Price>
    <WholesalePrice>0</WholesalePrice>
    <SalePrice>0</SalePrice>
    <OnSale>false</OnSale>
    <Quantity>1</Quantity>
    <picturePath>C:\Program Files\SCTech\Voodoo Cash Register\data\inventoryImages\imageNotAvailable.jpg</picturePath>
    <active>true</active>
    <displayOnWeb>true</displayOnWeb>
    <DateCreated>2012-10-06T16:13:01.484375-06:00</DateCreated>
  </InventoryItems>
</NewDataSet>